hius/__init__.py
hius/app.py
hius/httpcodes.py
hius/requests.py
hius/responses.py
hius/types.py
hius/handlers/__init__.py
hius/handlers/exceptions.py
hius/handlers/staticfiles.py
hius/openapi/__init__.py
hius/openapi/config.py
hius/openapi/middleware.py
hius/openapi/models.py
hius/openapi/template.py
hius/routing/__init__.py
hius/routing/endpoint.py
hius/routing/exceptions.py
hius/routing/lifespan.py
hius/routing/parser.py
hius/routing/router.py
hius/routing/routes.py
hius/routing/utils.py
hius-0.3.0.dist-info/METADATA
hius-0.3.0.dist-info/WHEEL
hius-0.3.0.dist-info/licenses/LICENSE
hius-0.3.0.dist-info/RECORD
